{
  "version": 2,
  "framework": "Schelling focal point detection + physical observables",
  "last_updated": "2026-04-26T22:03:11.737419+00:00",
  "design": "两层观测: 物理层(状态)+ 焦点层(转折). History in geopulse.db",
  "physical_observables": {
    "q1_attack_frequency": {
      "label": "IRGC袭击频率(次/天)",
      "source": "CENTCOM daily statements + UKMTO",
      "threshold_q2_start": "<2/day triggers minesweep clock",
      "threshold_decay": "<1/day for 5 consecutive days = fast decay",
      "history": [
        {
          "date": "2026-04-25",
          "est": "0.5次/天(停火期)",
          "note": "停火期IRGC仍有海峡袭扰：扣押2艘船、炮击1艘；导弹攻击较峰值降90%；停火延长3-5天",
          "source": "pipeline"
        },
        {
          "date": "2026-04-25",
          "est": "~0.5次/day (停火延期D17, 伊方4/25声称海峡'完全开放')",
          "note": "停火无限期延期(Trump 4/21 at巴方请求); 3-5天deadline 4/25-27到期; IRGC对美军直接攻击=0; 但IRGC每2-3天仍有商船骚扰(4/23炮击利比里亚旗船); 导弹能力削减90%(CENTCOM); Trump 4/23命令海军摧毁布雷船只; 13 KIA(+428 WIA官方,实际更高); 胡塞Red Sea独立运作",
          "source": "pipeline"
        },
        {
          "date": "2026-04-25",
          "est": "~0/day",
          "note": "停火自Apr 7起生效；Apr 21延长；IRGC将领vs文职谈判者分裂，无显著袭击",
          "source": "pipeline"
        },
        {
          "date": "2026-04-25",
          "est": "1-2/day",
          "note": "IRGC enforcing strait closure: vessel seizures + mine-laying ongoing; strait functionally closed",
          "source": "pipeline"
        },
        {
          "date": "2026-04-26",
          "est": "0-2次/天",
          "note": "停火期内IRGC大规模攻击暂停; 停火4月8日达成、4月21日延长; 战前攻击已下降90%(CENTCOM)",
          "source": "pipeline"
        },
        {
          "date": "2026-04-26",
          "est": "~0次/天(停火中)",
          "note": "4月7日停火，4月22日IRGC三连打为最后动能事件，停火已延长至月底",
          "source": "pipeline"
        },
        {
          "date": "2026-04-26",
          "est": "~3次/周(停火期)",
          "note": "停火自4月8日起，4月21日延长；峰值期3月1日62波/24小时，当前停火期IRGC主动袭击频率骤降至约3次/周，但双方均有零星违规",
          "source": "pipeline"
        },
        {
          "date": "2026-04-26",
          "est": "~0.1次/天",
          "note": "停火期间IRGC主动攻击近零；3月5日CENTCOM称弹道导弹攻击已下降90%；4月8日停火后进一步静默；Trump 4月22日给伊朗3-5天期限",
          "source": "pipeline"
        }
      ]
    },
    "q2_strait_transit": {
      "label": "海峡日通行量(mbd)",
      "source": "Vortexa/Kpler AIS (paid) or news estimates",
      "pre_crisis": "17-20 mbd",
      "current_est": "<2 mbd",
      "recovery_thresholds": {
        "partial": ">8 mbd for 3 days",
        "full": ">12 mbd for 5 days"
      },
      "history": [
        {
          "date": "2026-04-25",
          "est": "~5%正常水平(3艘/24h)",
          "note": "双重封锁：美国封锁伊朗港口+IRGC控制海峡；4/21仅3艘通行/24h；中俄印等白名单国家船只部分可通行；伊方声称完全开放但IRGC不配合",
          "source": "pipeline"
        },
        {
          "date": "2026-04-25",
          "est": "~5艘/day(4%正常水平) + 伊方4/25声称'完全开放'待核实",
          "note": "4/24: 5艘/24h(Windward); 战前基准138艘/天; 870艘船滞留波斯湾; 双重封锁持续(美封锁伊港+IRGC控海峡); 4/25关键信号: 市场据报道Iran称海峡'completely open'→Brent压力/S&P创新高; 但AIS确认数量极低; 伊朗内部IRGC vs 平民政府分裂执行",
          "source": "pipeline"
        },
        {
          "date": "2026-04-25",
          "est": "5 vessels/24h",
          "note": "较危机前~100+/天下降95%；500-700艘船滞留波斯湾；美伊双重封锁",
          "source": "pipeline"
        },
        {
          "date": "2026-04-25",
          "est": "3-5 ships/day",
          "note": "Apr 25: 3-5 ships/day vs normal 60-140; Apr 23 all 5 transits 'dark' AIS; 870 vessels trapped in Gulf; <5% of normal",
          "source": "pipeline"
        },
        {
          "date": "2026-04-26",
          "est": "3-5艘/天(正常60-140)",
          "note": "4月25日仅5艘过境; 双重封锁持续; 700+艘>10000DWT货船滞留波斯湾; AIS信号全暗",
          "source": "pipeline"
        },
        {
          "date": "2026-04-26",
          "est": "3-5艘/天(正常60-140)",
          "note": "4月23日仅5艘通过，均走北线走廊，AIS全暗，500-700艘船滞留波斯湾",
          "source": "pipeline"
        },
        {
          "date": "2026-04-26",
          "est": "3-5艘/天",
          "note": "战前均值约130艘/天；4月20日仅3艘(最低点)，4月23日5艘全部走北部通道且AIS全关闭；约500-700艘>10000吨船只滞留波斯湾；美伊双重封锁自4月13日起",
          "source": "pipeline"
        },
        {
          "date": "2026-04-26",
          "est": "~5艘/天(正常138艘/天的3.6%)",
          "note": "4月23日仅5艘通行，全部AIS关闭；4月20-25周均3-7艘；停滞船只500-700艘；Polymarket 99%概率4月底前不恢复正常",
          "source": "pipeline"
        }
      ]
    },
    "q3_spr_release_rate": {
      "label": "SPR实际释放速率(mbd)",
      "source": "DOE weekly report (每周三)",
      "announced": "400M bbl global, 172M bbl US",
      "delivery_timeline": "120 days per DOE, first barrels end of W3",
      "max_physical_rate": "4.4 mbd (US SPR pump limit)",
      "history": [
        {
          "date": "2026-04-25",
          "est": "~1.4Mb/天",
          "note": "172Mb IEA协调释放计划，120天交付期；首批45.2Mb合同3月20日签约已开始交付；4/9再发30Mb征询；EIA 4/17当周库存持续消耗",
          "source": "pipeline"
        },
        {
          "date": "2026-04-25",
          "est": "~1.43M bbl/day (172M/120天 IEA计划)",
          "note": "EIA周报4/22(截至4/17): SPR~409M bbl; 第三批30M sweet crude RFP处理中(West Hackberry 4/9); 汽油全国均价~.18/gal(+29.5% YoY); IEA协调400M全球总释放; 下期EIA周报4/29发布",
          "source": "pipeline"
        },
        {
          "date": "2026-04-25",
          "est": "~1.43M bbl/day",
          "note": "172M桶/120天释放计划；IEA全球协调400M桶；Apr17当周库存意外增加193万桶",
          "source": "pipeline"
        },
        {
          "date": "2026-04-25",
          "est": "~1.4M bbl/day",
          "note": "172M bbl IEA emergency exchange over ~120 days from late March; 45.2M initial contracts awarded; DOE soliciting additional 30M bbl Apr 9",
          "source": "pipeline"
        },
        {
          "date": "2026-04-26",
          "est": "~143万桶/天(172M桶/120天)",
          "note": "IEA协调400M桶全球释放; 4月17日当周EIA报告显示汽油库存连续10周下降; 半量为借贷形式",
          "source": "pipeline"
        },
        {
          "date": "2026-04-26",
          "est": "~1.4M桶/天",
          "note": "IEA协调美国释放1.72亿桶/120天，已启动4520万桶交换，周报截至4月17日",
          "source": "pipeline"
        },
        {
          "date": "2026-04-26",
          "est": "~143万桶/天",
          "note": "IEA协调释放：美国172M桶/120天=约143万桶/天；初始合同3月20日生效，涉及BryanMound/WestHackberry/BayouChoctaw；总储量415M桶(容量58%)",
          "source": "pipeline"
        },
        {
          "date": "2026-04-26",
          "est": "~10M桶/周",
          "note": "DOE启动172M桶SPR紧急互换(IEA 400M桶协调计划)，约120天交付=1.43M桶/天；第一批已授出45.2M桶；4月17日当周汽油库存连续第10周下降",
          "source": "pipeline"
        }
      ]
    }
  },
  "focal_signals": {
    "fp1_china_action": {
      "priority": "★★★★★",
      "label": "中国实质行动(唯一可行聚点注入)",
      "status": "active-limited",
      "last_check": "2026-04-26",
      "findings": "中国特使翟隽穿梭外交；王毅与各方通话26次；中巴发布5点和平方案(3月31日)；但美国扣押中伊货船(4月19日)、指控中国向伊朗运送MANPAD；中俄否决UNSC海峡护航决议——中国在外交层面活跃但实质影响力受限"
    },
    "fp2_us_signal_inconsistency": {
      "priority": "★★★★☆",
      "label": "美方信号包内部矛盾(承诺解锁前导)",
      "status": "contradictory-high",
      "last_check": "2026-04-26",
      "findings": "Trump宣布护航但海军表示未准备好；4月21日单方面延长停火同时维持海上封锁；4月25日取消Witkoff/Kushner巴基斯坦行；4月22日给伊朗3-5天期限；行动与表态高度矛盾"
    },
    "fp3_face_saving_framework": {
      "priority": "★★★★☆",
      "label": "面子工程原材料出现",
      "status": "stalled",
      "last_check": "2026-04-26",
      "findings": "框架存在(伊朗10点方案+美国15点方案)；Trump称伊方提议是'可工作基础'；但4月25日谈判彻底破裂：伊朗外长离开巴基斯坦、美方取消访问；IRGC与文职谈判团队内部公开撕裂"
    },
    "fp4_cost_threshold": {
      "priority": "★★★☆☆",
      "label": "成本阈值的物理逼近",
      "status": "elevated-approaching-threshold",
      "last_check": "2026-04-26",
      "findings": "战争授权法5月1日60天截止；国会5次战争权力决议均被参议院共和党封杀(最近46-51)；众议院213-214险败；Gas .18/加仑(同比+29.5%)；美军死亡13人；Trump称不受时间表约束；Collins等共和党人松动"
    }
  },
  "noise_filter": {
    "rule": "按行为类型分类,不按人物分类",
    "noise": [
      "Trump推文/社交媒体(言辞)",
      "IRGC官方声明(言辞)",
      "巴盖伊等发言人声明(言辞)",
      "媒体'消息人士'报道(未验证)",
      "分析师价格预测(意见)"
    ],
    "signal": [
      "Trump签署行政令/军事命令(行动)",
      "美军实际调兵/部署变化(行动)",
      "IRGC实际攻击模式变化(行动)",
      "SPR实际释放/停止(行动)",
      "中国实际经济/军事动作(行动)"
    ],
    "key_distinction": "同一个人的言辞=噪声,行动=信号。Trump说'just for fun'=噪声。Trump命令打Kharg=信号。"
  },
  "pipeline_daily_checklist": [
    "1. 物理层: 更新Q1(袭击频率) + Q2(通行量) + Q3(SPR释放)",
    "2. 焦点层: 扫描fp1(中国动作) + fp2(美方矛盾) + fp3(退出框架) + fp4(成本阈值)",
    "3. 噪声过滤: 新闻分类为action vs rhetoric",
    "4. 结构性验证: 跑structural_verify检查盲区+停滞+链断裂",
    "5. DAG更新: 只有物理层变化或焦点层信号触发才更新概率"
  ]
}