{
  "version": 2,
  "framework": "Schelling focal point detection + physical observables",
  "last_updated": "2026-04-19T06:02:41.451407+00:00",
  "design": "两层观测: 物理层(状态)+ 焦点层(转折). History in geopulse.db",
  "physical_observables": {
    "q1_attack_frequency": {
      "label": "IRGC袭击频率(次/天)",
      "source": "CENTCOM daily statements + UKMTO",
      "threshold_q2_start": "<2/day triggers minesweep clock",
      "threshold_decay": "<1/day for 5 consecutive days = fast decay",
      "history": [
        {
          "date": "2026-04-17",
          "est": "~0/day (停火D11, blockade D5)",
          "note": "停火D11(4/8起); blockade D5运行中; CENTCOM暂停对伊空袭; IRGC直接攻击仍为零; 13 KIA+381 WIA(官方,停火期间无新伤亡); Trump 4/16新制裁2dozen伊朗石油运输实体(行动); USS Spruance拦截13艘含伊朗货船(行动); Trump 4/17称'not sure ceasefire needs to be extended'+deal 'looking very good'(言辞); 巴黎40+国escort会议今日(Macron+Starmer+Merz+Meloni): 纯防御性多国护航任务'when conditions are met'(行动:制度化准备); Israel-Lebanon 10天停火D2(4/16起); 停火4/22到期(5天); 60天WPR时限~5/1(14天)",
          "source": "pipeline"
        },
        {
          "date": "2026-04-17",
          "est": "~0/day (停火D12, blockade D6)",
          "note": "停火D12(4/8起); blockade D6运行中; CENTCOM暂停对伊空袭; IRGC直接攻击仍为零; 13 KIA+381 WIA(官方,停火期间无新伤亡); Iran FM 4/17宣布海峡'completely open'(行动:重大让步); 条件:与IRGC协调Larak路线+解冻伊朗资金; Trump称blockade'remains in full force'+deal'soon'(言辞vs行动矛盾); 巴黎49国escort会议结果: 12+国承诺参与'when conditions allow'(行动:制度化); Northwood下周军事规划峰会(行动); Trump告诉NATO盟友'stay away'(言辞:排斥盟友); 第二轮Islamabad谈判预计本周末; 停火4/22到期(4天); 60天WPR时限5/1(13天)",
          "source": "pipeline"
        },
        {
          "date": "2026-04-18",
          "est": "~0/day (停火D13, blockade D7)",
          "note": "停火D13(4/8起); blockade D7运行中; CENTCOM暂停对伊空袭; IRGC直接攻击仍为零; 13 KIA+373 WIA(官方,停火期间无新伤亡); Trump称talks may resume this week(NPR 4/15)(言辞); 'in principle agreement'延长停火(CNBC 4/14)(行动:政策讨论); 但Trump反对enrichment compromise(WaPo 4/14)(行动:红线); 核分歧:Iran 5年 vs US 20年暂停; 停火4/22到期(4天); 60天WPR时限~5/1(13天); Senate 47-52否决WPR第4次(4/15)(行动); House 213-214否决(4/16,差1票)(行动)",
          "source": "pipeline"
        },
        {
          "date": "2026-04-18",
          "est": "~0/day (停火D13, blockade D7)",
          "note": "停火D13(4/8起); blockade D7运行中; CENTCOM暂停对伊空袭; IRGC直接攻击仍为零; 13 KIA+373 WIA(官方,停火期间无新伤亡); 第二轮Islamabad谈判确认周一4/21举行(CNN 4/17引伊朗消息源)(行动:谈判重启!); 谈判代表预计周日抵达; Trump称'most main points finalized'+'go pretty quickly'(言辞vs核分歧5yr/20yr仍存); USS Ford+2驱逐舰已部署至Red Sea(行动:战备姿态); 停火4/22到期(4天); 60天WPR时限5/1(13天)",
          "source": "pipeline"
        },
        {
          "date": "2026-04-18",
          "est": "~0/day (停火D13, blockade D7)",
          "note": "停火D13(4/8起); blockade D7运行中; CENTCOM暂停对伊空袭; IRGC直接攻击仍为零; 13 KIA+373 WIA(官方,停火期间无新伤亡); 第二轮Islamabad谈判确认周一4/21(CNN 4/17)(行动); 核分歧5yr/20yr仍存; Rubio 4/18促欧洲重施制裁+警告Iran核能力(行动:鹰派政策推进); 停火4/22到期(4天); 60天WPR时限5/1(13天)",
          "source": "pipeline"
        },
        {
          "date": "2026-04-18",
          "est": "~0/day (停火D14, blockade D8)",
          "note": "停火D14(4/8起); blockade D8运行中; CENTCOM暂停对伊空袭; IRGC直接攻击仍为零; 13 KIA+373 WIA(官方,停火期间无新伤亡); IRGC 4/18宣布关闭海峡+据报向船只开火(CNN live/Wikipedia 4/18)(行动:重大升级!); 停火4/21到期(2天!); 第二轮Islamabad谈判预计4/21(Pakistan FM未确认具体日期); 核分歧5yr/20yr仍存; 60天WPR时限5/1(12天)",
          "source": "pipeline"
        },
        {
          "date": "2026-04-19",
          "est": "~0/day (停火D15, blockade D9)",
          "note": "停火D15(4/8起); blockade D9运行中; CENTCOM暂停对伊空袭; IRGC直接攻击美军仍为零; 但IRGC 4/18向商船开火(行动:重大升级); IRGC 4/19宣布海峡今晚起关闭直至美方解除blockade(行动:全面升级!); 13 KIA+373 WIA(官方,停火期间无新美军伤亡); 停火4/21-22到期(2-3天); 第二轮Islamabad谈判预计4/21但日期未确认(Middle East Monitor 4/18); 核分歧5yr/20yr仍存; 60天WPR时限5/1(12天)",
          "source": "pipeline"
        },
        {
          "date": "2026-04-19",
          "est": "~0/day (停火D15, blockade D9)",
          "note": "停火D15(4/8起); blockade D9运行中; CENTCOM暂停对伊空袭; IRGC直接攻击美军仍为零; 但IRGC 4/19向2艘印度油轮(Sanmar Herald+Jag Arnav)开火迫其掉头(行动:首次对非交战国商船动武!); IRGC 4/19重申海峡关闭+警告'靠近海峡视为与敌合作,违规船只将被打击'(行动:operational threat); 印度MEA召见伊朗大使Fathali抗议(行动:新国家被卷入); 13 KIA+373 WIA(官方,停火期间无新美军伤亡); Iran SNSC确认收到美方新提案via Pakistan正在审议(行动:谈判通道仍活); 停火4/21-22到期(2-3天); 60天WPR时限5/1(12天)",
          "source": "pipeline"
        }
      ]
    },
    "q2_strait_transit": {
      "label": "海峡日通行量(mbd)",
      "source": "Vortexa/Kpler AIS (paid) or news estimates",
      "pre_crisis": "17-20 mbd",
      "current_est": "<2 mbd",
      "recovery_thresholds": {
        "partial": ">8 mbd for 3 days",
        "full": ">12 mbd for 5 days"
      },
      "history": [
        {
          "date": "2026-04-17",
          "est": "~6-8艘/天 (blockade D5, 通行量减90%+)",
          "note": "blockade D5: CNBC 4/15: 通行量较战前下降90%(行动); 4/14:6艘(Kpler)/14艘(其他); 4/13:14艘; 4/12:17艘(3/1以来最忙); vs战前100-138艘/天; 600+船滞留; Pentagon称completely halted Iran sea trade; sanctioned tankers仍穿越(enforcement gap持续); 巴黎40+国escort会议今日4/17: 准备多国防御性护航(情报共享+扫雷+护航+邻国协调)(行动:制度化); Polymarket美军4/30前护航仅18%YES(行动:市场怀疑); 美海军仍未启动tanker escort; 保险仍拒覆盖; 油价波动: WTI一度+4%至后回落~.5",
          "source": "pipeline"
        },
        {
          "date": "2026-04-17",
          "est": "~10-50艘/天 (Iran宣布开放但实际恢复待验证)",
          "note": "MAJOR SHIFT: Iran FM 4/17宣布海峡'completely open to all commercial vessels'(行动:重大让步); 条件:与IRGC协调+走Larak路线+提交文件+部分付费; BBC: Iran says open but tracking shows few ships actually moving; Lloyd's: 50/72 transits via Iran协调路线(4/6-近期); US blockade on Iran ports 'remains in full force'(Trump); 保险仍拒覆盖; 油价暴跌11%(行动:市场定价开放); Brent~.89 WTI~.79; 但实际恢复需时间: 保险/IRGC协调/扫雷; vs战前100-138艘/天; 600+船仍滞留; 巴黎escort会议: 12+国承诺'when conditions allow'",
          "source": "pipeline"
        },
        {
          "date": "2026-04-18",
          "est": "~6-10艘/天 (blockade D7, Iran宣布开放但实际恢复缓慢)",
          "note": "blockade D7: Iran FM 4/17宣布海峡completely open(行动:重大让步); 但BBC/Lloyd's: 实际通行仍极低; CNBC 4/15: 通行量较战前下降90%(行动); 4/14仅6艘(Kpler); vs战前100-138艘/天; 600+船仍滞留; US blockade on Iran ports 'remains in full force'; 保险仍拒覆盖; 美海军仍未启动tanker escort(行动:承诺未兑现); 巴黎49国escort会议4/17: 12+国承诺参与when conditions allow(行动:制度化); Northwood下周军事规划峰会(行动); 油价波动: Brent~96 WTI~92-94",
          "source": "pipeline"
        },
        {
          "date": "2026-04-18",
          "est": "~6-10艘/天 (Iran宣布开放但实际恢复极慢)",
          "note": "blockade D7: Iran FM 4/17宣布海峡completely open(行动:重大让步); 但Maersk称'任何过境决定基于风险评估'(行动:航运巨头观望); IMO称正在'验证伊朗公告'(行动:未背书); BBC/Lloyd's: 实际通行仍极低; 汽油期货4/18跌破$2.95/gal(行动:市场定价开放); vs战前100-138艘/天; 600+船仍滞留; US blockade on Iran ports remains; 美海军仍未启动tanker escort; 巴黎49国escort: 12+国承诺when conditions allow(行动:制度化); Northwood下周军事规划峰会(行动); 保险仍拒覆盖",
          "source": "pipeline"
        },
        {
          "date": "2026-04-18",
          "est": "~6-10艘/天 (IRGC逆转FM开放宣言,恢复'之前状态')",
          "note": "CRITICAL: IRGC 4/18宣布Hormuz'returned to previous state'因US blockade持续(AlJazeera)(行动:逆转FM 4/17 completely open!); FM vs IRGC内部矛盾=IRGC实控海峡; US blockade remains in full force(Trump); 实际通行仍6-10艘/天vs战前100-138; 600+船仍滞留; Maersk称基于风险评估决定过境(行动:观望); IMO验证中未背书(行动); 保险仍拒覆盖; 巴黎49国escort: 12+国承诺when conditions allow(行动:制度化); Northwood下周军事规划峰会(行动)",
          "source": "pipeline"
        },
        {
          "date": "2026-04-18",
          "est": "~6-10艘/天 (IRGC关闭海峡,通行量持续极低)",
          "note": "blockade D8: IRGC 4/18宣布Hormuz returned to previous state+据报向船只开火(行动:逆转FM开放!); 通行量仍减90%+vs战前100-138艘/天; 600+船仍滞留; US blockade remains in full force; 保险仍拒覆盖; 美海军仍未启动tanker escort; 巴黎49国escort: 12+国承诺when conditions allow(行动:制度化); Northwood下周军事规划峰会(行动); Maersk观望; IMO未背书; Polymarket美军4/30前护航仅18%",
          "source": "pipeline"
        },
        {
          "date": "2026-04-19",
          "est": "~2-20艘/天 (IRGC宣布今晚起全面关闭海峡)",
          "note": "blockade D9: IRGC 4/19宣布海峡今晚起关闭直至美方解除blockade(行动:全面升级!逆转FM 4/17 completely open); IRGC 4/18已向商船开火(CNN/The National)(行动); IMF Portwatch: 2-20艘/天; vs战前100-138艘/天(减90%+); 600+船仍滞留; 油价4/18暴跌: WTI .83 Brent ~(FM开放信号); 但IRGC关闭=周一开盘将反弹; Maersk/IMO仍观望; 保险仍拒覆盖; Northwood军事规划峰会下周(行动:制度化); Polymarket美军4/30前护航仅18%",
          "source": "pipeline"
        },
        {
          "date": "2026-04-19",
          "est": "~0-5艘/天 (IRGC重申关闭+向印度船开火)",
          "note": "blockade D9: IRGC 4/19重申海峡关闭直至美方解除blockade(行动:FM 4/17 completely open彻底作废); IRGC 4/19向2艘印度油轮开火(Sanmar Herald+Jag Arnav)(行动:首次对第三国商船动武!); IRGC警告所有船只不得靠近海峡(行动:封锁执行升级); India MEA召见伊朗大使(行动:新利益相关方); 油价4/18暴跌10%+(WTI 83.83 Brent~89)(FM开放假信号); 但IRGC周末关闭+开火=周一开盘油价将暴涨反转; vs战前100-138艘/天; 600+船仍滞留; 保险更不可能覆盖(开火事件); Maersk/IMO继续观望; Northwood军事规划峰会下周(行动:制度化)",
          "source": "pipeline"
        }
      ]
    },
    "q3_spr_release_rate": {
      "label": "SPR实际释放速率(mbd)",
      "source": "DOE weekly report (每周三)",
      "announced": "400M bbl global, 172M bbl US",
      "delivery_timeline": "120 days per DOE, first barrels end of W3",
      "max_physical_rate": "4.4 mbd (US SPR pump limit)",
      "history": [
        {
          "date": "2026-04-17",
          "est": "~0.25 mbd净提取 (无新EIA数据,下次4/22)",
          "note": "无新EIA数据(下次4/22); 上期EIA 4/15(截至4/10): crude inventories -0.913M bbl; SPR~413M bbl维持(1980s最低); DOE第二批8.48M bbl已发放; DOE称delivering at record speeds; 30M bbl甜原油RFP 4/13截止(结果待公布); 172M/120天目标1.4mbd实际仅~0.25mbd(释放严重滞后); 汽油均价~.06(AAA mid-April,较峰值.25继续回落); 油价波动: WTI -95; 停火延长in-principle但未签署→释放节奏暂无变化",
          "source": "pipeline"
        },
        {
          "date": "2026-04-17",
          "est": "~0.59 mbd净提取 (EIA 4/15: SPR 409.2M bbl, -4.1M w/w)",
          "note": "EIA 4/15发布(截至4/10): SPR~409.2M bbl(-4.1M w/w≈0.59mbd)(行动:释放加速!); 此前仅0.25mbd→现翻倍+; DOE称delivering at record speeds(行动); 30M bbl甜原油RFP 4/13截止(结果待公布); 172M/120天目标1.4mbd实际0.59mbd(仍滞后但显著加速); SPR~409M为1980s以来最低; 汽油均价~.09-4.11(AAA mid-April,较峰值.25继续回落); 油价暴跌: Brent~.89 WTI~.79(Hormuz开放+谈判信号); 下次EIA报告4/22",
          "source": "pipeline"
        },
        {
          "date": "2026-04-18",
          "est": "~0.59 mbd净提取 (无新EIA数据,下次4/22)",
          "note": "无新EIA数据(下次4/22); 上期EIA 4/15(截至4/10): SPR~409.2M bbl(-4.1M w/w≈0.59mbd)(行动:释放加速); DOE称delivering at record speeds; 30M bbl甜原油RFP 4/13截止(结果待公布); 172M/120天目标1.4mbd实际0.59mbd(仍滞后但显著加速); SPR~409M为1980s以来最低; 汽油均价~.25(AAA week of 4/13); 油价: Brent~96 WTI~92-94; 停火延长in-principle→释放节奏暂无加速压力",
          "source": "pipeline"
        },
        {
          "date": "2026-04-18",
          "est": "~0.59 mbd净提取 (无新EIA数据,下次4/22)",
          "note": "无新EIA数据(下次4/22); 上期EIA 4/15(截至4/10): SPR~409.2M bbl(-4.1M w/w≈0.59mbd)(行动:释放加速); DOE称delivering at record speeds; 30M bbl甜原油RFP 4/13截止(结果待公布); 172M/120天目标1.4mbd实际0.59mbd(仍滞后但显著加速); SPR~409M为1980s以来最低; 汽油零售$4.254(AAA week 4/13); 汽油期货4/18跌至<$2.95(行动:正面信号); 油价: Brent~96 WTI~92-94; 下次EIA报告4/22",
          "source": "pipeline"
        },
        {
          "date": "2026-04-18",
          "est": "~0.59 mbd净提取 (无新EIA数据,下次4/22)",
          "note": "无新EIA数据(下次4/22); 上期EIA 4/15(截至4/10): SPR~409.2M bbl(-4.1M w/w≈0.59mbd)(行动:释放加速); DOE称delivering at record speeds; 172M/120天目标1.4mbd实际0.59mbd(仍滞后但加速); SPR~409M为1980s以来最低; 汽油零售$4.254(AAA week 4/13); 汽油期货跌破$2.95(行动:市场正面); 油价: Brent~96 WTI~92-94",
          "source": "pipeline"
        },
        {
          "date": "2026-04-18",
          "est": "~0.59 mbd净提取 (无新EIA数据,下次4/22)",
          "note": "无新EIA数据(下次4/22周二); 上期EIA 4/15(截至4/10): SPR~409.2M bbl(-4.1M w/w≈0.59mbd)(行动:释放加速); DOE称delivering at record speeds; 172M/120天目标1.4mbd实际0.59mbd(仍滞后但加速); SPR~409M为1980s以来最低; 汽油零售$4.254(AAA week 4/13); 油价: Brent~96 WTI~92-94(4/18收盘)",
          "source": "pipeline"
        },
        {
          "date": "2026-04-19",
          "est": "~0.59 mbd净提取 (无新EIA数据,下次4/22周二)",
          "note": "无新EIA数据(下次4/22周二); 上期EIA 4/15(截至4/10): SPR~409.2M bbl(-4.1M w/w≈0.59mbd)(行动:释放加速); DOE称delivering at record speeds; 172M/120天目标1.4mbd实际0.59mbd(仍滞后但加速); SPR~409M为1980s以来最低; 汽油零售.254(AAA week 4/13); 油价暴跌WTI .83(4/18收盘); 但IRGC关闭海峡=供应风险重新飙升→下周释放加速压力可能回升",
          "source": "pipeline"
        },
        {
          "date": "2026-04-19",
          "est": "~0.59 mbd净提取 (无新EIA数据,下次4/22周二)",
          "note": "无新EIA数据(下次4/22周二); 上期EIA 4/15(截至4/10): SPR~409.2M bbl(-4.1M w/w≈0.59mbd)(行动:释放加速); DOE称delivering at record speeds; 172M/120天目标1.4mbd实际0.59mbd(仍滞后但加速); SPR~409M为1980s以来最低; 汽油零售4.11-4.254(AAA mid-April); 油价暴跌WTI 83.83(4/18收盘); 但IRGC关闭海峡+向商船开火=供应风险骤升→下周释放加速压力回升; 30M bbl甜原油RFP结果待公布",
          "source": "pipeline"
        }
      ]
    }
  },
  "focal_signals": {
    "fp1_china_action": {
      "priority": "★★★★★",
      "label": "中国实质行动(唯一可行聚点注入)",
      "status": "marginalized-no-action-diplomacy-only",
      "last_check": "2026-04-19",
      "findings": "中国持续边缘化: CGTN/人民日报继续辩护否决权(言辞:自我辩护); 王毅26+通电话+翟隽5国斡旋无突破; 巴黎49国escort完全不含中国(行动:制度性排除); 新发展: Iran SNSC确认收到美方新提案via Pakistan(行动:Pakistan仍为事实调停人); 中国在新一轮提案中无角色; IRGC向印度船开火→India被卷入但中国未介入; 结构: 外交活跃但零军事/经济实质行动, 调停权完全在Pakistan"
    },
    "fp2_us_signal_inconsistency": {
      "priority": "★★★★☆",
      "label": "美方信号包内部矛盾(承诺解锁前导)",
      "status": "extreme-contradiction-irgc-fires-on-third-country-ships",
      "last_check": "2026-04-19",
      "findings": "矛盾达到新峰值: (1)IRGC 4/19向2艘印度油轮开火(行动:首次对非交战国商船动武=ceasefire实质性违反!); (2)IRGC重申海峡关闭+威胁打击靠近船只(行动:FM完全失控); (3)India召见伊朗大使(行动:新front); (4)Iran SNSC审议美方新提案via Pakistan(行动:外交线仍活); (5)FM vs IRGC公开分裂升级:FM 4/17 completely open→IRGC 4/18关闭→IRGC 4/19开火(行动序列:IRGC完全压制外交派); (6)停火4/21-22到期(2-3天); (7)Senate 47-52+House 213-214(差1票); (8)60天WPR 5/1(12天); 结构: IRGC对外国商船动武=ceasefire从名义维持变为实质崩溃"
    },
    "fp3_face_saving_framework": {
      "priority": "★★★★☆",
      "label": "面子工程原材料出现",
      "status": "critical-ceasefire-collapsing-irgc-fires-on-ships",
      "last_check": "2026-04-19",
      "findings": "退出框架濒临崩溃: (1)停火4/21-22到期仅2-3天; (2)IRGC向印度商船开火=ceasefire实质违反(虽非直接US-Iran军事冲突); (3)IRGC威胁打击所有靠近船只(行动:升级); (4)Iran SNSC审议美方新提案(行动:外交窗口极窄); (5)第二轮Islamabad日期仍未确认(4/21?); (6)核分歧5yr/20yr最大障碍; (7)巴黎49国escort+Northwood下周军事规划=ceasefire破裂备案制度化(行动); (8)India被卷入=新利益相关方/复杂度增加; 结构: IRGC连续escalation+ceasefire倒计时+新提案审议中=最后48小时决定战/和"
    },
    "fp4_cost_threshold": {
      "priority": "★★★☆☆",
      "label": "成本阈值的物理逼近",
      "status": "extreme-market-disconnect-record-highs-vs-irgc-escalation",
      "last_check": "2026-04-19",
      "findings": "市场与现实严重脱节: 4/18收盘: S&P 7126(+1.20%连续3日新高!); VIX 17.48(-2.56%恐慌回落); Gold 4879(+1.48%避险仍在); WTI 83.83(暴跌10%+); Brent~89(暴跌10%+); 市场定价FM开放+ceasefire延长; 但IRGC 4/19向印度船开火+重申关闭=周一开盘将暴力反转(oil涨/equity跌); 汽油零售4.11-4.254; 军事13 KIA+373 WIA; 政治WPR 5/1硬期限(12天)+House差1票(213-214); 结构: 周五市场定价de-escalation vs 周末IRGC actual escalation=周一将是最大single-day repricing之一"
    }
  },
  "noise_filter": {
    "rule": "按行为类型分类,不按人物分类",
    "noise": [
      "Trump推文/社交媒体(言辞)",
      "IRGC官方声明(言辞)",
      "巴盖伊等发言人声明(言辞)",
      "媒体'消息人士'报道(未验证)",
      "分析师价格预测(意见)"
    ],
    "signal": [
      "Trump签署行政令/军事命令(行动)",
      "美军实际调兵/部署变化(行动)",
      "IRGC实际攻击模式变化(行动)",
      "SPR实际释放/停止(行动)",
      "中国实际经济/军事动作(行动)"
    ],
    "key_distinction": "同一个人的言辞=噪声,行动=信号。Trump说'just for fun'=噪声。Trump命令打Kharg=信号。"
  },
  "pipeline_daily_checklist": [
    "1. 物理层: 更新Q1(袭击频率) + Q2(通行量) + Q3(SPR释放)",
    "2. 焦点层: 扫描fp1(中国动作) + fp2(美方矛盾) + fp3(退出框架) + fp4(成本阈值)",
    "3. 噪声过滤: 新闻分类为action vs rhetoric",
    "4. 结构性验证: 跑structural_verify检查盲区+停滞+链断裂",
    "5. DAG更新: 只有物理层变化或焦点层信号触发才更新概率"
  ]
}